quantables/__init__.py
quantables/csv_importer/__init__.py
quantables/csv_importer/csv_importer.py
quantables/csv_importer/csv_preview.py
quantables/csv_importer/csv_widgets.py
quantables/string_utils.py
quantables/table_model.py
quantables/widgets/__init__.py
quantables/widgets/quantity_form.py
quantables/widgets/quantity_widget.py
quantables-0.1.3.dist-info/LICENSE
quantables-0.1.3.dist-info/METADATA
quantables-0.1.3.dist-info/WHEEL
quantables-0.1.3.dist-info/RECORD
