Metadata-Version: 2.3
Name: quantables
Version: 0.1.3
Summary: A Python package for managing unit-aware quantities with uncertainties, tailored for PySide6/Qt GUIs.
License: MIT
Keywords: CSV,CSV Importer,pandas,pint,unit-aware,measurement,uncertainty,PySide6,Qt,data import,data visualization,unit conversion,data parsing,file selection,unit quantities,physical,quantities,unit,conversion,error propagation,uncertainties,uncertainty calculations,standard deviation,science,series,dataframe
Author: Christian Schreinemachers (Cs137)
Requires-Python: >=3.9,<3.14
Classifier: Intended Audience :: Developers
Classifier: Intended Audience :: Education
Classifier: Intended Audience :: Science/Research
Classifier: Operating System :: OS Independent
Classifier: Programming Language :: Python :: 3
Classifier: Programming Language :: Python :: 3.9
Classifier: Programming Language :: Python :: 3.10
Classifier: Programming Language :: Python :: 3.11
Classifier: Programming Language :: Python :: 3.12
Classifier: Programming Language :: Python :: 3.13
Classifier: Programming Language :: Python :: 3 :: Only
Classifier: Topic :: Education
Classifier: Topic :: Scientific/Engineering
Classifier: Topic :: Software Development :: Libraries :: Python Modules
Classifier: Topic :: Utilities
Requires-Dist: pandas (>=2.2.3,<3.0.0)
Requires-Dist: pint (>=0.24.4,<0.25.0)
Requires-Dist: pyside6 (>=6.9.0,<7.0.0)
Requires-Dist: uncertainties (>=3.2.3,<4.0.0)
Requires-Dist: unpaac (>=0.1.4,<0.2.0)
Project-URL: Changelog, https://codeberg.org/Cs137/QuanTables/src/branch/main/CHANGELOG.md
Project-URL: Issues, https://codeberg.org/Cs137/QuanTables/issues
Project-URL: Repository, https://codeberg.org/Cs137/QuanTables
